sourmash_plugin_betterplot.py
sourmash_plugin_betterplot-0.5.6.dist-info/licenses/LICENSE
sourmash_plugin_betterplot-0.5.6.dist-info/METADATA
sourmash_plugin_betterplot-0.5.6.dist-info/WHEEL
sourmash_plugin_betterplot-0.5.6.dist-info/entry_points.txt
sourmash_plugin_betterplot-0.5.6.dist-info/top_level.txt
sourmash_plugin_betterplot-0.5.6.dist-info/RECORD
