Metadata-Version: 2.4
Name: sourmash_plugin_betterplot
Version: 0.5.6
Summary: sourmash plugin for improved plotting/viz and cluster examination.
Requires-Python: >=3.11
License-File: LICENSE
Requires-Dist: sourmash<5,>=4.9.4
Requires-Dist: sourmash_utils>=0.2
Requires-Dist: matplotlib
Requires-Dist: numpy
Requires-Dist: scipy
Requires-Dist: scikit-learn
Requires-Dist: seaborn
Requires-Dist: upsetplot
Requires-Dist: matplotlib_venn
Requires-Dist: pandas
Requires-Dist: plotly
Requires-Dist: biopython
Requires-Dist: ete3
Requires-Dist: kaleido
Requires-Dist: pyqt5
Requires-Dist: legacy_cgi
Requires-Dist: squarify==0.4.4
Requires-Dist: taxburst>=0.3.1
Dynamic: license-file
